subsearch/__init__.py
subsearch/__main__.py
subsearch/core.py
subsearch/data/__init__.py
subsearch/data/guid.py
subsearch/data/language_data.toml
subsearch/data/version.py
subsearch/globals/__init__.py
subsearch/globals/_logging.py
subsearch/globals/constants.py
subsearch/globals/dataclasses.py
subsearch/globals/decorators.py
subsearch/globals/exceptions.py
subsearch/globals/metaclasses.py
subsearch/globals/thread_handle.py
subsearch/gui/__init__.py
subsearch/gui/common_utils.py
subsearch/gui/resource_loader.py
subsearch/gui/screen_manager.py
subsearch/gui/system_tray.py
subsearch/gui/resources/__init__.py
subsearch/gui/resources/config.py
subsearch/gui/resources/assets/__init__.py
subsearch/gui/resources/assets/spritesheet.png
subsearch/gui/resources/assets/subsearch.ico
subsearch/gui/resources/styles/__init__.py
subsearch/gui/resources/styles/sprites.tcl
subsearch/gui/resources/styles/style_subsearch.tcl
subsearch/gui/resources/styles/theme_setter.tcl
subsearch/gui/screens/__init__.py
subsearch/gui/screens/download_manager.py
subsearch/gui/screens/language_options.py
subsearch/gui/screens/search_options.py
subsearch/gui/screens/subsearch_options.py
subsearch/providers/__init__.py
subsearch/providers/common_utils.py
subsearch/providers/opensubtitles.py
subsearch/providers/subsource.py
subsearch/providers/yifysubtitles.py
subsearch/utils/__init__.py
subsearch/utils/imdb_lookup.py
subsearch/utils/io_app.py
subsearch/utils/io_file_system.py
subsearch/utils/io_toml.py
subsearch/utils/io_winreg.py
subsearch/utils/string_parser.py
subsearch/utils/update.py
subsearch-2.47.2.dist-info/licenses/LICENSE
subsearch-2.47.2.dist-info/METADATA
subsearch-2.47.2.dist-info/WHEEL
subsearch-2.47.2.dist-info/entry_points.txt
subsearch-2.47.2.dist-info/top_level.txt
subsearch-2.47.2.dist-info/RECORD
