Metadata-Version: 2.4
Name: Subsearch
Version: 2.47.2
Summary: Subsearch
Author: vagabondHustler
Author-email: vagabondHustler.github@gmail.com
License: MIT license
Project-URL: repository, https://github.com/vagabondHustler/subsearch
Keywords: subtitles,sub,srt,tool,tools,download,movies,shows,scrape,opensubtitles,subscene,subsearch,subtitles,yifysubtitles
Platform: win32
Classifier: Intended Audience :: Developers
Classifier: Intended Audience :: End Users/Desktop
Classifier: Operating System :: Microsoft :: Windows
Classifier: Programming Language :: Python :: 3.12
Classifier: Topic :: Multimedia :: Video
Classifier: Topic :: Utilities
Requires-Python: >=3.12
License-File: LICENSE
Requires-Dist: picologging==0.9.3
Requires-Dist: cloudscraper==1.2.71
Requires-Dist: num2words==0.5.14
Requires-Dist: packaging==24.2
Requires-Dist: pillow==11.1.0
Requires-Dist: pystray==0.19.5
Requires-Dist: requests==2.32.3
Requires-Dist: selectolax==0.3.28
Requires-Dist: toml==0.10.2
Provides-Extra: build
Requires-Dist: build==1.2.2.post1; extra == "build"
Requires-Dist: cx_Freeze==8.1.0; extra == "build"
Requires-Dist: twine==6.1.0; extra == "build"
Requires-Dist: psutil==7.0.0; extra == "build"
Provides-Extra: lint
Requires-Dist: black==25.1.0; extra == "lint"
Requires-Dist: isort==6.0.1; extra == "lint"
Provides-Extra: tests
Requires-Dist: pytest-cov==6.1.1; extra == "tests"
Requires-Dist: pytest==8.3.5; extra == "tests"
Requires-Dist: tox==4.25.0; extra == "tests"
Requires-Dist: python-dotenv==1.1.0; extra == "tests"
Provides-Extra: tools
Requires-Dist: pyperclip==1.9.0; extra == "tools"
Provides-Extra: type
Requires-Dist: mypy==1.15.0; extra == "type"
Dynamic: license-file
